pyfroc/__about__.py
pyfroc/__init__.py
pyfroc/coords.py
pyfroc/keys.py
pyfroc/miniball_util.py
pyfroc/pyfroc.py
pyfroc/sample.py
pyfroc/signals.py
pyfroc/utils.py
pyfroc/data/sample_experiment.zip
pyfroc/loaders/__init__.py
pyfroc/loaders/base_loader.py
pyfroc/loaders/osirix_roi_series.py
pyfroc/loaders/seg_nrrd.py
pyfroc/loaders/simple_loader.py
pyfroc/raters/__init__.py
pyfroc/raters/base_rater.py
pyfroc/raters/within_lesion_rater.py
pyfroc/writers/__init__.py
pyfroc/writers/base_writer.py
pyfroc/writers/response_lesion_images.py
pyfroc/writers/rjafroc.py
pyfroc-0.3.5.dist-info/METADATA
pyfroc-0.3.5.dist-info/WHEEL
pyfroc-0.3.5.dist-info/entry_points.txt
pyfroc-0.3.5.dist-info/licenses/LICENSE
pyfroc-0.3.5.dist-info/RECORD
