Metadata-Version: 2.3
Name: pyfroc
Version: 0.3.5
Summary: python framework for FROC/AFROC analysis
Project-URL: Homepage, https://github.com/akchan/pyfroc
Project-URL: Issues, https://github.com/akchan/pyfroc/issues
Author-email: Satoshi Funayama <akchan.acts@gmail.com>
License-File: LICENSE
Classifier: License :: OSI Approved :: GNU General Public License v3 (GPLv3)
Classifier: Operating System :: OS Independent
Classifier: Programming Language :: Python :: 3
Requires-Python: >=3.9
Requires-Dist: bidict>=0.23.1
Requires-Dist: matching>=1.4.3
Requires-Dist: miniballcpp>=0.2.3
Requires-Dist: numpy<2.0.0,>=1.2.0
Requires-Dist: openpyxl>=3.1.4
Requires-Dist: pandas>=2.2.2
Requires-Dist: pydicom>=2.4.4
Requires-Dist: pynrrd>=1.0.0
Requires-Dist: pytypedstream>=0.1.0
Requires-Dist: scikit-image>=0.23.2
Requires-Dist: tcia-utils
Requires-Dist: tqdm>=4.66.4
